pyTRT/__init__.py
pyTRT/methods/GATRT.py
pyTRT/methods/ILS.py
pyTRT/methods/__init__.py
pyTRT/methods/baseclass.py
pyTRT/utils/__init__.py
pyTRT/utils/load_data.py
pytrt-0.0.3.dist-info/licenses/LICENSE
test/__init__.py
test/test_ils.py
test/test_load_data.py
pytrt-0.0.3.dist-info/METADATA
pytrt-0.0.3.dist-info/WHEEL
pytrt-0.0.3.dist-info/top_level.txt
pytrt-0.0.3.dist-info/RECORD
