Metadata-Version: 2.4
Name: pyTRT
Version: 0.0.3
Summary: A package for TRT analysis
Home-page: https://github.com/wouterpeere/pytrt
Author: Wouter Peere
Author-email: info@ghetool.eu
License: BSD 3-Clause License
Keywords: Geothermal,Ground-source,Ground heat exchangers,TRT,thermal response test
Classifier: Development Status :: 5 - Production/Stable
Classifier: Intended Audience :: Science/Research
Classifier: License :: OSI Approved :: BSD License
Classifier: Natural Language :: English
Classifier: Operating System :: OS Independent
Classifier: Programming Language :: Python :: 3
Classifier: Programming Language :: Python :: 3 :: Only
Classifier: Topic :: Scientific/Engineering
Classifier: Topic :: Utilities
Requires-Python: >=3.10
License-File: LICENSE
Requires-Dist: numpy>=1.26.4
Requires-Dist: pandas>=1.4.3
Requires-Dist: pygfunction>=2.3.0
Requires-Dist: GHEtool>=2.3.3
Provides-Extra: doc
Requires-Dist: numpydoc>=1.7.0; extra == "doc"
Requires-Dist: recommonmark>=0.7.1; extra == "doc"
Requires-Dist: sphinx>=7.3.7; extra == "doc"
Provides-Extra: testing
Requires-Dist: pytest>=7.4.4; extra == "testing"
Requires-Dist: pytest-cov>=6.1.1; extra == "testing"
Dynamic: license-file
